builting_package/__init__.py
builting_package/calculator.py
simplecalculator_mike_tyson-0.1.0.dist-info/METADATA
simplecalculator_mike_tyson-0.1.0.dist-info/WHEEL
simplecalculator_mike_tyson-0.1.0.dist-info/top_level.txt
simplecalculator_mike_tyson-0.1.0.dist-info/RECORD
