Metadata-Version: 2.4
Name: simplecalculator-mike-tyson
Version: 0.1.0
Summary: A simple arithmetic calculator in Python
Author: Mike
